{
	"info": {
		"_postman_id": "warung-os-backend",
		"name": "WarungOS Backend API",
		"description": "Comprehensive test collection for WarungOS Backend. Includes Happy Paths, Edge Cases, and automated workflows.",
		"schema": "https://schema.getpostman.com/json/collection/v2.1.0/collection.json"
	},
	"item": [
		{
			"name": "0. Health Checks",
			"item": [
				{
					"name": "Check System Health",
					"event": [
						{
							"listen": "test",
							"script": {
								"exec": [
									"pm.test(\"Status code is 200\", function () {",
									"    pm.response.to.have.status(200);",
									"});",
									"",
									"pm.test(\"System is healthy\", function () {",
									"    var jsonData = pm.response.json();",
									"    pm.expect(jsonData.status).to.eql(\"healthy\");",
									"    pm.expect(jsonData.services.database).to.eql(\"up\");",
									"});"
								],
								"type": "text/javascript"
							}
						}
					],
					"request": {
						"method": "GET",
						"header": [],
						"url": {
							"raw": "{{base_url}}/health",
							"host": [
								"{{base_url}}"
							],
							"path": [
								"health"
							]
						}
					}
				}
			]
		},
		{
			"name": "1. Products Management",
			"item": [
				{
					"name": "Create Product (Indomie)",
					"event": [
						{
							"listen": "test",
							"script": {
								"exec": [
									"pm.test(\"Status code is 201\", function () {",
									"    pm.response.to.have.status(201);",
									"});",
									"",
									"var jsonData = pm.response.json();",
									"pm.environment.set(\"product_id_1\", jsonData.data.id);",
									"pm.environment.set(\"product_sku_1\", jsonData.data.sku);",
									"console.log(\"Created Product 1: \" + jsonData.data.id);"
								],
								"type": "text/javascript"
							}
						}
					],
					"request": {
						"method": "POST",
						"header": [],
						"body": {
							"mode": "raw",
							"raw": "{\n    \"name\": \"Indomie Goreng\",\n    \"sku\": \"IND-GRG-001\",\n    \"barcode\": \"8998888123456\",\n    \"category_id\": null,\n    \"unit\": \"pcs\",\n    \"base_price\": 3500,\n    \"cost_price\": 2800,\n    \"is_stock_active\": true,\n    \"current_stock\": 100,\n    \"min_stock_alert\": 10,\n    \"pricing_tiers\": [\n        {\"name\": \"Grosir\", \"min_quantity\": 12, \"price\": 3000}\n    ]\n}",
							"options": {
								"raw": {
									"language": "json"
								}
							}
						},
						"url": {
							"raw": "{{base_url}}/api/v1/products",
							"host": [
								"{{base_url}}"
							],
							"path": [
								"api",
								"v1",
								"products"
							]
						}
					}
				},
				{
					"name": "Create Product (Beras - No Stock Tracking)",
					"event": [
						{
							"listen": "test",
							"script": {
								"exec": [
									"pm.test(\"Status code is 201\", function () {",
									"    pm.response.to.have.status(201);",
									"});",
									"",
									"var jsonData = pm.response.json();",
									"pm.environment.set(\"product_id_2\", jsonData.data.id);",
									"console.log(\"Created Product 2: \" + jsonData.data.id);"
								],
								"type": "text/javascript"
							}
						}
					],
					"request": {
						"method": "POST",
						"header": [],
						"body": {
							"mode": "raw",
							"raw": "{\n    \"name\": \"Jasa Bungkus Kado\",\n    \"unit\": \"service\",\n    \"base_price\": 5000,\n    \"cost_price\": 0,\n    \"is_stock_active\": false\n}",
							"options": {
								"raw": {
									"language": "json"
								}
							}
						},
						"url": {
							"raw": "{{base_url}}/api/v1/products",
							"host": [
								"{{base_url}}"
							],
							"path": [
								"api",
								"v1",
								"products"
							]
						}
					}
				},
				{
					"name": "Create Product (Validation Error - Edge Case)",
					"event": [
						{
							"listen": "test",
							"script": {
								"exec": [
									"pm.test(\"Status code is 422 Unprocessable Entity\", function () {",
									"    pm.response.to.have.status(422);",
									"});",
									"",
									"pm.test(\"Returns validation errors\", function () {",
									"    var jsonData = pm.response.json();",
									"    pm.expect(jsonData.error).to.include(\"Validation failed\");",
									"});"
								],
								"type": "text/javascript"
							}
						}
					],
					"request": {
						"method": "POST",
						"header": [],
						"body": {
							"mode": "raw",
							"raw": "{\n    \"name\": \"\",\n    \"base_price\": -5000\n}",
							"options": {
								"raw": {
									"language": "json"
								}
							}
						},
						"url": {
							"raw": "{{base_url}}/api/v1/products",
							"host": [
								"{{base_url}}"
							],
							"path": [
								"api",
								"v1",
								"products"
							]
						}
					}
				},
				{
					"name": "Get Product List",
					"event": [
						{
							"listen": "test",
							"script": {
								"exec": [
									"pm.test(\"Status code is 200\", function () {",
									"    pm.response.to.have.status(200);",
									"});",
									"",
									"pm.test(\"Contains data\", function () {",
									"    var jsonData = pm.response.json();",
									"    pm.expect(jsonData.data.length).to.be.above(0);",
									"});"
								],
								"type": "text/javascript"
							}
						}
					],
					"request": {
						"method": "GET",
						"header": [],
						"url": {
							"raw": "{{base_url}}/api/v1/products?per_page=10&page=1",
							"host": [
								"{{base_url}}"
							],
							"path": [
								"api",
								"v1",
								"products"
							],
							"query": [
								{
									"key": "per_page",
									"value": "10"
								},
								{
									"key": "page",
									"value": "1"
								}
							]
						}
					}
				},
				{
					"name": "Search Product by Barcode",
					"event": [
						{
							"listen": "test",
							"script": {
								"exec": [
									"pm.test(\"Status code is 200\", function () {",
									"    pm.response.to.have.status(200);",
									"});",
									"",
									"pm.test(\"Correct product returned\", function () {",
									"    var jsonData = pm.response.json();",
									"    pm.expect(jsonData.data.name).to.eql(\"Indomie Goreng\");",
									"});"
								],
								"type": "text/javascript"
							}
						}
					],
					"request": {
						"method": "GET",
						"header": [],
						"url": {
							"raw": "{{base_url}}/api/v1/products/search?barcode=8998888123456",
							"host": [
								"{{base_url}}"
							],
							"path": [
								"api",
								"v1",
								"products",
								"search"
							],
							"query": [
								{
									"key": "barcode",
									"value": "8998888123456"
								}
							]
						}
					}
				}
			]
		},
		{
			"name": "2. Inventory Management",
			"item": [
				{
					"name": "Restock Product (Purchase)",
					"event": [
						{
							"listen": "test",
							"script": {
								"exec": [
									"pm.test(\"Status code is 201\", function () {",
									"    pm.response.to.have.status(201);",
									"});"
								],
								"type": "text/javascript"
							}
						}
					],
					"request": {
						"method": "POST",
						"header": [],
						"body": {
							"mode": "raw",
							"raw": "{\n    \"product_id\": \"{{product_id_1}}\",\n    \"quantity\": 50,\n    \"cost_per_unit\": 2700,\n    \"notes\": \"Restock mingguan\"\n}",
							"options": {
								"raw": {
									"language": "json"
								}
							}
						},
						"url": {
							"raw": "{{base_url}}/api/v1/inventory/restock",
							"host": [
								"{{base_url}}"
							],
							"path": [
								"api",
								"v1",
								"inventory",
								"restock"
							]
						}
					}
				},
				{
					"name": "Adjust Stock (Corrections)",
					"event": [
						{
							"listen": "test",
							"script": {
								"exec": [
									"pm.test(\"Status code is 201\", function () {",
									"    pm.response.to.have.status(201);",
									"});"
								],
								"type": "text/javascript"
							}
						}
					],
					"request": {
						"method": "POST",
						"header": [],
						"body": {
							"mode": "raw",
							"raw": "{\n    \"product_id\": \"{{product_id_1}}\",\n    \"quantity\": -2,\n    \"reason\": \"Barang rusak/expired\"\n}",
							"options": {
								"raw": {
									"language": "json"
								}
							}
						},
						"url": {
							"raw": "{{base_url}}/api/v1/inventory/adjust",
							"host": [
								"{{base_url}}"
							],
							"path": [
								"api",
								"v1",
								"inventory",
								"adjust"
							]
						}
					}
				}
			]
		},
		{
			"name": "3. Customers",
			"item": [
				{
					"name": "Create Customer (John Doe)",
					"event": [
						{
							"listen": "test",
							"script": {
								"exec": [
									"pm.test(\"Status code is 201\", function () {",
									"    pm.response.to.have.status(201);",
									"});",
									"",
									"var jsonData = pm.response.json();",
									"pm.environment.set(\"customer_id\", jsonData.data.id);"
								],
								"type": "text/javascript"
							}
						}
					],
					"request": {
						"method": "POST",
						"header": [],
						"body": {
							"mode": "raw",
							"raw": "{\n    \"name\": \"John Doe\",\n    \"phone\": \"081234567890\",\n    \"credit_limit\": 100000,\n    \"address\": \"Jl. Warung No. 1\"\n}",
							"options": {
								"raw": {
									"language": "json"
								}
							}
						},
						"url": {
							"raw": "{{base_url}}/api/v1/customers",
							"host": [
								"{{base_url}}"
							],
							"path": [
								"api",
								"v1",
								"customers"
							]
						}
					}
				},
				{
					"name": "Create Customer (Bad Credit - Edge Case)",
					"event": [
						{
							"listen": "test",
							"script": {
								"exec": [
									"pm.test(\"Status code is 201\", function () {",
									"    pm.response.to.have.status(201);",
									"});",
									"",
									"var jsonData = pm.response.json();",
									"pm.environment.set(\"bad_customer_id\", jsonData.data.id);"
								],
								"type": "text/javascript"
							}
						}
					],
					"request": {
						"method": "POST",
						"header": [],
						"body": {
							"mode": "raw",
							"raw": "{\n    \"name\": \"Mr. Broke\",\n    \"credit_limit\": 0\n}",
							"options": {
								"raw": {
									"language": "json"
								}
							}
						},
						"url": {
							"raw": "{{base_url}}/api/v1/customers",
							"host": [
								"{{base_url}}"
							],
							"path": [
								"api",
								"v1",
								"customers"
							]
						}
					}
				}
			]
		},
		{
			"name": "4. POS Transactions",
			"item": [
				{
					"name": "Calculate Cart (Preview)",
					"event": [
						{
							"listen": "test",
							"script": {
								"exec": [
									"pm.test(\"Status code is 200\", function () {",
									"    pm.response.to.have.status(200);",
									"});",
									"",
									"var jsonData = pm.response.json();",
									"pm.test(\"Calculates correct price\", function () {",
									"    // 13 pcs > 12 (Grosir 3000)",
									"    // 13 * 3000 = 39000",
									"    pm.expect(jsonData.data.subtotal).to.eql(39000);",
									"    pm.expect(jsonData.data.items[0].tier_name).to.eql(\"Grosir\");",
									"});"
								],
								"type": "text/javascript"
							}
						}
					],
					"request": {
						"method": "POST",
						"header": [],
						"body": {
							"mode": "raw",
							"raw": "{\n    \"items\": [\n        {\n            \"product_id\": \"{{product_id_1}}\",\n            \"quantity\": 13\n        }\n    ]\n}",
							"options": {
								"raw": {
									"language": "json"
								}
							}
						},
						"url": {
							"raw": "{{base_url}}/api/v1/transactions/calculate",
							"host": [
								"{{base_url}}"
							],
							"path": [
								"api",
								"v1",
								"transactions",
								"calculate"
							]
						}
					}
				},
				{
					"name": "Checkout - Cash Payment",
					"event": [
						{
							"listen": "test",
							"script": {
								"exec": [
									"pm.test(\"Status code is 201\", function () {",
									"    pm.response.to.have.status(201);",
									"});",
									"",
									"var jsonData = pm.response.json();",
									"pm.test(\"Successful transaction\", function () {",
									"    pm.expect(jsonData.data.status).to.eql(\"completed\");",
									"    pm.expect(jsonData.data.payment_method).to.eql(\"cash\");",
									"    pm.expect(jsonData.data.change_amount).to.be.above(0);",
									"});"
								],
								"type": "text/javascript"
							}
						}
					],
					"request": {
						"method": "POST",
						"header": [],
						"body": {
							"mode": "raw",
							"raw": "{\n    \"items\": [\n        {\n            \"product_id\": \"{{product_id_1}}\",\n            \"quantity\": 2\n        },\n        {\n            \"product_id\": \"{{product_id_2}}\",\n            \"quantity\": 1\n        }\n    ],\n    \"payment_method\": \"cash\",\n    \"amount_paid\": 20000,\n    \"cashier_name\": \"Kasir 1\"\n}",
							"options": {
								"raw": {
									"language": "json"
								}
							}
						},
						"url": {
							"raw": "{{base_url}}/api/v1/transactions",
							"host": [
								"{{base_url}}"
							],
							"path": [
								"api",
								"v1",
								"transactions"
							]
						}
					}
				},
				{
					"name": "Checkout - Kasbon (Debt) Success",
					"event": [
						{
							"listen": "test",
							"script": {
								"exec": [
									"pm.test(\"Status code is 201\", function () {",
									"    pm.response.to.have.status(201);",
									"});",
									"",
									"var jsonData = pm.response.json();",
									"pm.environment.set(\"transaction_id_kasbon\", jsonData.data.id);"
								],
								"type": "text/javascript"
							}
						}
					],
					"request": {
						"method": "POST",
						"header": [],
						"body": {
							"mode": "raw",
							"raw": "{\n    \"customer_id\": \"{{customer_id}}\",\n    \"items\": [\n        {\n            \"product_id\": \"{{product_id_1}}\",\n            \"quantity\": 10\n        }\n    ],\n    \"payment_method\": \"kasbon\",\n    \"amount_paid\": 0,\n    \"notes\": \"Hutang dulu boss\"\n}",
							"options": {
								"raw": {
									"language": "json"
								}
							}
						},
						"url": {
							"raw": "{{base_url}}/api/v1/transactions",
							"host": [
								"{{base_url}}"
							],
							"path": [
								"api",
								"v1",
								"transactions"
							]
						}
					}
				},
				{
					"name": "Checkout - Kasbon Limit Exceeded (Edge Case)",
					"event": [
						{
							"listen": "test",
							"script": {
								"exec": [
									"pm.test(\"Status code is 400\", function () {",
									"    pm.response.to.have.status(400);",
									"});",
									"",
									"pm.test(\"Error message correct\", function () {",
									"    pm.expect(pm.response.text()).to.include(\"limit exceeded\");",
									"});"
								],
								"type": "text/javascript"
							}
						}
					],
					"request": {
						"method": "POST",
						"header": [],
						"body": {
							"mode": "raw",
							"raw": "{\n    \"customer_id\": \"{{bad_customer_id}}\",\n    \"items\": [\n        {\n            \"product_id\": \"{{product_id_1}}\",\n            \"quantity\": 50\n        }\n    ],\n    \"payment_method\": \"kasbon\",\n    \"amount_paid\": 0\n}",
							"options": {
								"raw": {
									"language": "json"
								}
							}
						},
						"url": {
							"raw": "{{base_url}}/api/v1/transactions",
							"host": [
								"{{base_url}}"
							],
							"path": [
								"api",
								"v1",
								"transactions"
							]
						}
					}
				},
				{
					"name": "Checkout - Insufficient Stock (Edge Case)",
					"event": [
						{
							"listen": "test",
							"script": {
								"exec": [
									"pm.test(\"Status code is 400\", function () {",
									"    pm.response.to.have.status(400);",
									"});",
									"",
									"pm.test(\"Error indicates stock issue\", function () {",
									"    pm.expect(pm.response.text()).to.include(\"insufficient stock\");",
									"});"
								],
								"type": "text/javascript"
							}
						}
					],
					"request": {
						"method": "POST",
						"header": [],
						"body": {
							"mode": "raw",
							"raw": "{\n    \"items\": [\n        {\n            \"product_id\": \"{{product_id_1}}\",\n            \"quantity\": 99999\n        }\n    ],\n    \"payment_method\": \"cash\",\n    \"amount_paid\": 999999999\n}",
							"options": {
								"raw": {
									"language": "json"
								}
							}
						},
						"url": {
							"raw": "{{base_url}}/api/v1/transactions",
							"host": [
								"{{base_url}}"
							],
							"path": [
								"api",
								"v1",
								"transactions"
							]
						}
					}
				},
				{
					"name": "5. Kasbon Management",
					"item": [
						{
							"name": "Get Customer Kasbon History",
							"event": [
								{
									"listen": "test",
									"script": {
										"exec": [
											"pm.test(\"Status code is 200\", function () {",
											"    pm.response.to.have.status(200);",
											"});",
											"",
											"var jsonData = pm.response.json();",
											"pm.expect(jsonData.data.length).to.be.above(0);"
										],
										"type": "text/javascript"
									}
								}
							],
							"request": {
								"method": "GET",
								"header": [],
								"url": {
									"raw": "{{base_url}}/api/v1/customers/{{customer_id}}/kasbon",
									"host": [
										"{{base_url}}"
									],
									"path": [
										"api",
										"v1",
										"customers",
										"{{customer_id}}",
										"kasbon"
									]
								}
							}
						},
						{
							"name": "Record Kasbon Payment",
							"event": [
								{
									"listen": "test",
									"script": {
										"exec": [
											"pm.test(\"Status code is 201\", function () {",
											"    pm.response.to.have.status(201);",
											"});"
										],
										"type": "text/javascript"
									}
								}
							],
							"request": {
								"method": "POST",
								"header": [],
								"body": {
									"mode": "raw",
									"raw": "{\n    \"amount\": 10000,\n    \"notes\": \"Bayar cicilan pertama\"\n}",
									"options": {
										"raw": {
											"language": "json"
										}
									}
								},
								"url": {
									"raw": "{{base_url}}/api/v1/customers/{{customer_id}}/kasbon/pay",
									"host": [
										"{{base_url}}"
									],
									"path": [
										"api",
										"v1",
										"customers",
										"{{customer_id}}",
										"kasbon",
										"pay"
									]
								}
							}
						}
					]
				},
				{
					"name": "6. Reporting",
					"item": [
						{
							"name": "Get Dashboard",
							"event": [
								{
									"listen": "test",
									"script": {
										"exec": [
											"pm.test(\"Status code is 200\", function () {",
											"    pm.response.to.have.status(200);",
											"});",
											"",
											"var jsonData = pm.response.json();",
											"pm.expect(jsonData.data.today.total_transactions).to.be.at.least(1);"
										],
										"type": "text/javascript"
									}
								}
							],
							"request": {
								"method": "GET",
								"header": [],
								"url": {
									"raw": "{{base_url}}/api/v1/reports/dashboard",
									"host": [
										"{{base_url}}"
									],
									"path": [
										"api",
										"v1",
										"reports",
										"dashboard"
									]
								}
							}
						},
						{
							"name": "Get Daily Report",
							"request": {
								"method": "GET",
								"header": [],
								"url": {
									"raw": "{{base_url}}/api/v1/reports/daily",
									"host": [
										"{{base_url}}"
									],
									"path": [
										"api",
										"v1",
										"reports",
										"daily"
									]
								}
							}
						}
					]
				},
				{
					"name": "7. Clean Up (Optional)",
					"item": [
						{
							"name": "Cancel Transaction (Void)",
							"event": [
								{
									"listen": "test",
									"script": {
										"exec": [
											"pm.test(\"Status code is 200\", function () {",
											"    pm.response.to.have.status(200);",
											"});"
										],
										"type": "text/javascript"
									}
								}
							],
							"request": {
								"method": "POST",
								"header": [],
								"url": {
									"raw": "{{base_url}}/api/v1/transactions/{{transaction_id_kasbon}}/cancel",
									"host": [
										"{{base_url}}"
									],
									"path": [
										"api",
										"v1",
										"transactions",
										"{{transaction_id_kasbon}}",
										"cancel"
									]
								}
							}
						}
					]
				}
			]
		}
	],
	"variable": [
		{
			"key": "base_url",
			"value": "http://localhost:8080",
			"type": "string"
		}
	]
}
